BCemu/BaryonEffectsEmulator.py
BCemu/__init__.py
BCemu/datasets.py
BCemu/download.py
BCemu/functions.py
BCemu/kpls.py
BCemu/input_data/README.rst
BCemu/input_data/galaxy_clusters_gas_constraints.xlsx
bcemu-1.1.4.dist-info/licenses/LICENSE
bcemu-1.1.4.dist-info/METADATA
bcemu-1.1.4.dist-info/WHEEL
bcemu-1.1.4.dist-info/top_level.txt
bcemu-1.1.4.dist-info/RECORD
