Metadata-Version: 2.4
Name: BCemu
Version: 1.1.4
Summary: Using emulators to implement baryonic effects.
Home-page: https://github.com/sambit-giri/BCemu.git
Author: Sambit Giri
Author-email: sambit.giri@gmail.com
License-File: LICENSE
Requires-Dist: cython
Requires-Dist: numpy
Requires-Dist: scipy
Requires-Dist: matplotlib
Requires-Dist: astropy
Requires-Dist: scikit-learn
Requires-Dist: smt==1.0.0
Requires-Dist: wget
Requires-Dist: pandas
Requires-Dist: importlib-resources
Requires-Dist: pytest
Requires-Dist: nose
Dynamic: author
Dynamic: author-email
Dynamic: description
Dynamic: description-content-type
Dynamic: home-page
Dynamic: license-file
Dynamic: requires-dist
Dynamic: summary
